README.md
setup.py
distributions_MTL/Binomialdistribution.py
distributions_MTL/Gaussiandistribution.py
distributions_MTL/Generaldistribution.py
distributions_MTL/__init__.py
distributions_MTL.egg-info/PKG-INFO
distributions_MTL.egg-info/SOURCES.txt
distributions_MTL.egg-info/dependency_links.txt
distributions_MTL.egg-info/not-zip-safe
distributions_MTL.egg-info/top_level.txt