Metadata-Version: 1.0
Name: distributions-MTL
Version: 0.2
Summary: Gaussian distributions
Home-page: UNKNOWN
Author: Matt LaDuke
Author-email: UNKNOWN
License: UNKNOWN
Platform: UNKNOWN
